MANIFEST.in
README.txt
setup.cfg
setup.py
docs/HISTORY.txt
horae/__init__.py
horae.js.jqplot.egg-info/PKG-INFO
horae.js.jqplot.egg-info/SOURCES.txt
horae.js.jqplot.egg-info/dependency_links.txt
horae.js.jqplot.egg-info/entry_points.txt
horae.js.jqplot.egg-info/namespace_packages.txt
horae.js.jqplot.egg-info/not-zip-safe
horae.js.jqplot.egg-info/requires.txt
horae.js.jqplot.egg-info/top_level.txt
horae/js/__init__.py
horae/js/jqplot/MIT-LICENSE.txt
horae/js/jqplot/README.txt
horae/js/jqplot/__init__.py
horae/js/jqplot/changes.txt
horae/js/jqplot/copyright.txt
horae/js/jqplot/gpl-2.0.txt
horae/js/jqplot/jqPlotCssStyling.txt
horae/js/jqplot/jqPlotOptions.txt
horae/js/jqplot/optionsTutorial.txt
horae/js/jqplot/resource.py
horae/js/jqplot/usage.txt
horae/js/jqplot/docs/index.html
horae/js/jqplot/docs/files/MIT-LICENSE-txt.html
horae/js/jqplot/docs/files/changes-txt.html
horae/js/jqplot/docs/files/gpl-2-0-txt.html
horae/js/jqplot/docs/files/jqPlotCssStyling-txt.html
horae/js/jqplot/docs/files/jqPlotOptions-txt.html
horae/js/jqplot/docs/files/jqplot-axisLabelRenderer-js.html
horae/js/jqplot/docs/files/jqplot-axisTickRenderer-js.html
horae/js/jqplot/docs/files/jqplot-canvasGridRenderer-js.html
horae/js/jqplot/docs/files/jqplot-core-js.html
horae/js/jqplot/docs/files/jqplot-divTitleRenderer-js.html
horae/js/jqplot/docs/files/jqplot-lineRenderer-js.html
horae/js/jqplot/docs/files/jqplot-linearAxisRenderer-js.html
horae/js/jqplot/docs/files/jqplot-markerRenderer-js.html
horae/js/jqplot/docs/files/jqplot-shadowRenderer-js.html
horae/js/jqplot/docs/files/jqplot-shapeRenderer-js.html
horae/js/jqplot/docs/files/jqplot-themeEngine-js.html
horae/js/jqplot/docs/files/jqplot-toImage-js.html
horae/js/jqplot/docs/files/optionsTutorial-txt.html
horae/js/jqplot/docs/files/usage-txt.html
horae/js/jqplot/docs/files/images/background.jpg
horae/js/jqplot/docs/files/images/basicline.png
horae/js/jqplot/docs/files/images/basiclogaxis.png
horae/js/jqplot/docs/files/images/basiclogoptions.png
horae/js/jqplot/docs/files/images/basicoptions.png
horae/js/jqplot/docs/files/images/dualaxis.png
horae/js/jqplot/docs/files/images/logo.jpg
horae/js/jqplot/docs/files/images/navdocs.png
horae/js/jqplot/docs/files/images/navdocsover.png
horae/js/jqplot/docs/files/images/navdownload.png
