Metadata-Version: 1.0
Name: horae.js.jqplot
Version: 1.0.0b2
Summary: Provides the jqPlot jQuery plugin as fanstatic resources
Home-page: UNKNOWN
Author: Simon Kaeser
Author-email: skaeser@gmail.com
License: GPL
Platform: UNKNOWN
Classifier: Programming Language :: Python
